lzwfile/__init__.py
lzwfile-0.1.5.dist-info/LICENSE
lzwfile-0.1.5.dist-info/METADATA
lzwfile-0.1.5.dist-info/WHEEL
lzwfile-0.1.5.dist-info/top_level.txt
lzwfile-0.1.5.dist-info/RECORD
