Metadata-Version: 2.1
Name: lzwfile
Version: 0.1.5
Summary: Python module for decoding compressed lzw files
Home-page: https://github.com/JJJados/lzwfile
Author: Jayden Laturnus
Author-email: jaydenlaturnus@gmail.com
License: MIT
Keywords: lzw
Platform: UNKNOWN
Classifier: Programming Language :: Python :: 3
Classifier: License :: OSI Approved :: MIT License
Requires-Python: >=3.6.0
